[
  {
    "id": 1039590872,
    "name": "portfolio-app",
    "full_name": "keepsake666/portfolio-app",
    "description": null,
    "html_url": "https://github.com/keepsake666/portfolio-app",
    "homepage": null,
    "language": "TypeScript",
    "stargazers_count": 0,
    "forks_count": 0,
    "updated_at": "2025-10-19T15:16:44Z",
    "topics": [],
    "visibility": "public",
    "private": false,
    "fork": false,
    "owner": {
      "login": null,
      "avatar_url": null
    },
    "license": null
  },
  {
    "id": 1046457317,
    "name": "ToDo-Mindbox-",
    "full_name": "keepsake666/ToDo-Mindbox-",
    "description": "test task for Mindbox",
    "html_url": "https://github.com/keepsake666/ToDo-Mindbox-",
    "homepage": "https://to-do-mindbox.vercel.app",
    "language": "TypeScript",
    "stargazers_count": 0,
    "forks_count": 0,
    "updated_at": "2025-08-29T08:45:46Z",
    "topics": [],
    "visibility": "public",
    "private": false,
    "fork": false,
    "owner": {
      "login": null,
      "avatar_url": null
    },
    "license": null
  },
  {
    "id": 922773058,
    "name": "TOP",
    "full_name": "keepsake666/TOP",
    "description": "Веб-приложение по учебным материалам",
    "html_url": "https://github.com/keepsake666/TOP",
    "homepage": "https://top-app-delta.vercel.app",
    "language": "TypeScript",
    "stargazers_count": 0,
    "forks_count": 0,
    "updated_at": "2025-08-29T08:15:44Z",
    "topics": [],
    "visibility": "public",
    "private": false,
    "fork": false,
    "owner": {
      "login": null,
      "avatar_url": null
    },
    "license": null
  },
  {
    "id": 526050781,
    "name": "keepsake666",
    "full_name": "keepsake666/keepsake666",
    "description": null,
    "html_url": "https://github.com/keepsake666/keepsake666",
    "homepage": null,
    "language": null,
    "stargazers_count": 0,
    "forks_count": 0,
    "updated_at": "2025-08-17T17:50:39Z",
    "topics": [],
    "visibility": "public",
    "private": false,
    "fork": false,
    "owner": {
      "login": null,
      "avatar_url": null
    },
    "license": null
  },
  {
    "id": 615147864,
    "name": "kupipodariday-backend",
    "full_name": "keepsake666/kupipodariday-backend",
    "description": "API для сервиса вишлистов",
    "html_url": "https://github.com/keepsake666/kupipodariday-backend",
    "homepage": "",
    "language": "TypeScript",
    "stargazers_count": 0,
    "forks_count": 0,
    "updated_at": "2025-08-17T15:29:57Z",
    "topics": [],
    "visibility": "public",
    "private": false,
    "fork": false,
    "owner": {
      "login": null,
      "avatar_url": null
    },
    "license": null
  },
  {
    "id": 578605475,
    "name": "algorithms",
    "full_name": "keepsake666/algorithms",
    "description": "Эта работа заточена на анимацию и поэтапное отображение работы алгоритма, что позволит вам детальнее понять каждый шаг его работы.",
    "html_url": "https://github.com/keepsake666/algorithms",
    "homepage": "",
    "language": "TypeScript",
    "stargazers_count": 0,
    "forks_count": 0,
    "updated_at": "2025-08-17T15:29:11Z",
    "topics": [],
    "visibility": "public",
    "private": false,
    "fork": false,
    "owner": {
      "login": null,
      "avatar_url": null
    },
    "license": null
  },
  {
    "id": 451712181,
    "name": "mesto-project",
    "full_name": "keepsake666/mesto-project",
    "description": "Одностроничный сайт, который содержит в себе информацию о профиле пользователя и галерею с фотографиями.Проект: Место",
    "html_url": "https://github.com/keepsake666/mesto-project",
    "homepage": "",
    "language": "JavaScript",
    "stargazers_count": 0,
    "forks_count": 0,
    "updated_at": "2025-08-17T15:28:53Z",
    "topics": [],
    "visibility": "public",
    "private": false,
    "fork": false,
    "owner": {
      "login": null,
      "avatar_url": null
    },
    "license": null
  },
  {
    "id": 504124893,
    "name": "react-burger",
    "full_name": "keepsake666/react-burger",
    "description": "Десктоп веб-приложение для сборки и заказа космических бургеров.",
    "html_url": "https://github.com/keepsake666/react-burger",
    "homepage": "",
    "language": "TypeScript",
    "stargazers_count": 0,
    "forks_count": 0,
    "updated_at": "2025-08-17T15:28:35Z",
    "topics": [],
    "visibility": "public",
    "private": false,
    "fork": false,
    "owner": {
      "login": null,
      "avatar_url": null
    },
    "license": null
  },
  {
    "id": 1038480141,
    "name": "task-list-app",
    "full_name": "keepsake666/task-list-app",
    "description": "Современное приложение для управления задачами, созданное на React, TypeScript и Vite с полной оптимизацией производительности.",
    "html_url": "https://github.com/keepsake666/task-list-app",
    "homepage": "https://task-list-app-azure.vercel.app",
    "language": "TypeScript",
    "stargazers_count": 0,
    "forks_count": 0,
    "updated_at": "2025-08-17T15:27:37Z",
    "topics": [],
    "visibility": "public",
    "private": false,
    "fork": false,
    "owner": {
      "login": null,
      "avatar_url": null
    },
    "license": null
  },
  {
    "id": 1035926637,
    "name": "task-list",
    "full_name": "keepsake666/task-list",
    "description": null,
    "html_url": "https://github.com/keepsake666/task-list",
    "homepage": null,
    "language": "JavaScript",
    "stargazers_count": 0,
    "forks_count": 0,
    "updated_at": "2025-08-14T09:16:40Z",
    "topics": [],
    "visibility": "public",
    "private": false,
    "fork": false,
    "owner": {
      "login": null,
      "avatar_url": null
    },
    "license": null
  },
  {
    "id": 728969711,
    "name": "djoni-tuna-back",
    "full_name": "keepsake666/djoni-tuna-back",
    "description": null,
    "html_url": "https://github.com/keepsake666/djoni-tuna-back",
    "homepage": "https://djoni-tuna-back.vercel.app",
    "language": "JavaScript",
    "stargazers_count": 0,
    "forks_count": 0,
    "updated_at": "2023-12-08T05:27:36Z",
    "topics": [],
    "visibility": "public",
    "private": false,
    "fork": false,
    "owner": {
      "login": null,
      "avatar_url": null
    },
    "license": null
  },
  {
    "id": 718462707,
    "name": "djoni-tuna",
    "full_name": "keepsake666/djoni-tuna",
    "description": null,
    "html_url": "https://github.com/keepsake666/djoni-tuna",
    "homepage": "https://djoni-tuna.vercel.app",
    "language": "TypeScript",
    "stargazers_count": 0,
    "forks_count": 0,
    "updated_at": "2023-12-06T05:06:19Z",
    "topics": [],
    "visibility": "public",
    "private": false,
    "fork": false,
    "owner": {
      "login": null,
      "avatar_url": null
    },
    "license": null
  },
  {
    "id": 674009076,
    "name": "graphics-card-shop",
    "full_name": "keepsake666/graphics-card-shop",
    "description": null,
    "html_url": "https://github.com/keepsake666/graphics-card-shop",
    "homepage": null,
    "language": "TypeScript",
    "stargazers_count": 0,
    "forks_count": 0,
    "updated_at": "2023-09-07T11:05:53Z",
    "topics": [],
    "visibility": "public",
    "private": false,
    "fork": false,
    "owner": {
      "login": null,
      "avatar_url": null
    },
    "license": null
  },
  {
    "id": 429253394,
    "name": "how-to-learn",
    "full_name": "keepsake666/how-to-learn",
    "description": "How to learn",
    "html_url": "https://github.com/keepsake666/how-to-learn",
    "homepage": null,
    "language": "HTML",
    "stargazers_count": 0,
    "forks_count": 0,
    "updated_at": "2023-06-16T11:00:20Z",
    "topics": [],
    "visibility": "public",
    "private": false,
    "fork": false,
    "owner": {
      "login": null,
      "avatar_url": null
    },
    "license": null
  },
  {
    "id": 601990010,
    "name": "mesto-project-plus",
    "full_name": "keepsake666/mesto-project-plus",
    "description": "Репозитория проекта Mesto (Web-Plus)",
    "html_url": "https://github.com/keepsake666/mesto-project-plus",
    "homepage": null,
    "language": "TypeScript",
    "stargazers_count": 0,
    "forks_count": 0,
    "updated_at": "2023-02-26T04:16:07Z",
    "topics": [],
    "visibility": "public",
    "private": false,
    "fork": false,
    "owner": {
      "login": null,
      "avatar_url": null
    },
    "license": null
  },
  {
    "id": 526053836,
    "name": "antonkomarev",
    "full_name": "keepsake666/antonkomarev",
    "description": null,
    "html_url": "https://github.com/keepsake666/antonkomarev",
    "homepage": null,
    "language": null,
    "stargazers_count": 0,
    "forks_count": 0,
    "updated_at": "2022-06-15T04:39:17Z",
    "topics": [],
    "visibility": "public",
    "private": false,
    "fork": true,
    "owner": {
      "login": null,
      "avatar_url": null
    },
    "license": null
  },
  {
    "id": 438516912,
    "name": "russian-travel",
    "full_name": "keepsake666/russian-travel",
    "description": "Проект: Путешествие по России",
    "html_url": "https://github.com/keepsake666/russian-travel",
    "homepage": null,
    "language": "HTML",
    "stargazers_count": 0,
    "forks_count": 0,
    "updated_at": "2021-12-26T04:18:12Z",
    "topics": [],
    "visibility": "public",
    "private": false,
    "fork": false,
    "owner": {
      "login": null,
      "avatar_url": null
    },
    "license": null
  }
]
